hta_helloworld_pkg/__init__.py
hta_helloworld_pkg/helloworld.py
example_pkg_hta_helloworld-0.0.3.dist-info/LICENSE
example_pkg_hta_helloworld-0.0.3.dist-info/METADATA
example_pkg_hta_helloworld-0.0.3.dist-info/WHEEL
example_pkg_hta_helloworld-0.0.3.dist-info/top_level.txt
example_pkg_hta_helloworld-0.0.3.dist-info/RECORD
