Metadata-Version: 2.1
Name: example-pkg-hta-helloworld
Version: 0.0.3
Summary: A hellowold example package
Home-page: https://github.com/howtoautomateinth/awesome-python
Author: Howtoautomate.in.th
Author-email: mart@howtoautomate.in.th
License: UNKNOWN
Platform: UNKNOWN
Classifier: Programming Language :: Python :: 3
Classifier: License :: OSI Approved :: MIT License
Classifier: Operating System :: OS Independent
Requires-Python: >=3.6
